{
  "playerId": 8483515,
  "playerName": "Juraj Slafkovský",
  "team": "MTL",
  "position": "L",
  "season": 2026,
  "lastUpdated": "2026-06-14T15:17:16.177535",
  "reg": {
    "totalGames": 82,
    "szn": {
      "slot": {
        "shotsOnGoal": 67,
        "goals": 17,
        "shootingPctg": 0.2537,
        "sogPercentile": 0.7403,
        "goalsPercentile": 0.8338
      },
      "highSlot": {
        "shotsOnGoal": 17,
        "goals": 4,
        "shootingPctg": 0.2353,
        "sogPercentile": 0.816,
        "goalsPercentile": 0.8632
      },
      "leftCircle": {
        "shotsOnGoal": 22,
        "goals": 3,
        "shootingPctg": 0.1364,
        "sogPercentile": 0.9039,
        "goalsPercentile": 0.8795
      },
      "rightCircle": {
        "shotsOnGoal": 20,
        "goals": 2,
        "shootingPctg": 0.1,
        "sogPercentile": 0.8632,
        "goalsPercentile": 0.7687
      },
      "cornerLeft": {
        "shotsOnGoal": 9,
        "goals": 1,
        "shootingPctg": 0.1111,
        "sogPercentile": 0.8933,
        "goalsPercentile": 0.408
      },
      "cornerRight": {
        "shotsOnGoal": 11,
        "goals": 0,
        "shootingPctg": 0.0,
        "sogPercentile": 0.9275,
        "goalsPercentile": 0.0
      },
      "pointLeft": {
        "shotsOnGoal": 1,
        "goals": 0,
        "shootingPctg": 0.0,
        "sogPercentile": 0.3013,
        "goalsPercentile": 0.0
      },
      "pointRight": {
        "shotsOnGoal": 2,
        "goals": 0,
        "shootingPctg": 0.0,
        "sogPercentile": 0.5033,
        "goalsPercentile": 0.0
      },
      "pointCenter": {
        "shotsOnGoal": 2,
        "goals": 0,
        "shootingPctg": 0.0,
        "sogPercentile": 0.4886,
        "goalsPercentile": 0.0
      },
      "total": {
        "shotsOnGoal": 151,
        "goals": 27,
        "shootingPctg": 0.1788
      },
      "totals": {
        "all": {
          "shotsOnGoal": 180,
          "goals": 30,
          "shootingPctg": 0.1667,
          "sogPercentile": 0.8893,
          "goalsPercentile": 0.9283,
          "sogLeagueAvg": 85.9138,
          "goalsLeagueAvg": 11.1545
        },
        "high": {
          "shotsOnGoal": 67,
          "goals": 17,
          "shootingPctg": 0.2537,
          "sogPercentile": 0.8974,
          "goalsPercentile": 0.9397,
          "sogLeagueAvg": 31.6244,
          "goalsLeagueAvg": 6.1935
        },
        "long": {
          "shotsOnGoal": 5,
          "goals": 0,
          "shootingPctg": 0.0,
          "sogPercentile": 0.4251,
          "goalsPercentile": 0.0,
          "sogLeagueAvg": 8.0081,
          "goalsLeagueAvg": 0.3106
        },
        "mid": {
          "shotsOnGoal": 59,
          "goals": 9,
          "shootingPctg": 0.1525,
          "sogPercentile": 0.873,
          "goalsPercentile": 0.8893,
          "sogLeagueAvg": 27.2195,
          "goalsLeagueAvg": 3.3008
        }
      }
    },
    "l5": null,
    "l10": null,
    "l20": null
  },
  "playoffs": {
    "totalGames": 19,
    "szn": {
      "slot": {
        "shotsOnGoal": 21,
        "goals": 3,
        "shootingPctg": 0.1429,
        "sogPercentile": 0.973,
        "goalsPercentile": 0.4639
      },
      "highSlot": {
        "shotsOnGoal": 2,
        "goals": 0,
        "shootingPctg": 0.0,
        "sogPercentile": 0.6306,
        "goalsPercentile": 0.0
      },
      "leftCircle": {
        "shotsOnGoal": 6,
        "goals": 0,
        "shootingPctg": 0.0,
        "sogPercentile": 0.9505,
        "goalsPercentile": 0.0
      },
      "rightCircle": {
        "shotsOnGoal": 3,
        "goals": 2,
        "shootingPctg": 0.6667,
        "sogPercentile": 0.7748,
        "goalsPercentile": 0.9865
      },
      "cornerLeft": {
        "shotsOnGoal": 4,
        "goals": 0,
        "shootingPctg": 0.0,
        "sogPercentile": 0.491,
        "goalsPercentile": 0.0
      },
      "cornerRight": {
        "shotsOnGoal": 4,
        "goals": 0,
        "shootingPctg": 0.0,
        "sogPercentile": 0.4978,
        "goalsPercentile": 0.0
      },
      "pointLeft": {
        "shotsOnGoal": 0,
        "goals": 0,
        "shootingPctg": 0.0,
        "sogPercentile": 0.0,
        "goalsPercentile": 0.0
      },
      "pointRight": {
        "shotsOnGoal": 0,
        "goals": 0,
        "shootingPctg": 0.0,
        "sogPercentile": 0.0,
        "goalsPercentile": 0.0
      },
      "pointCenter": {
        "shotsOnGoal": 1,
        "goals": 0,
        "shootingPctg": 0.0,
        "sogPercentile": 0.7162,
        "goalsPercentile": 0.0
      },
      "total": {
        "shotsOnGoal": 41,
        "goals": 5,
        "shootingPctg": 0.122
      },
      "totals": {
        "all": {
          "shotsOnGoal": 48,
          "goals": 6,
          "shootingPctg": 0.125,
          "sogPercentile": 0.9685,
          "goalsPercentile": 0.9234,
          "sogLeagueAvg": 15.0135,
          "goalsLeagueAvg": 1.8341
        },
        "high": {
          "shotsOnGoal": 21,
          "goals": 3,
          "shootingPctg": 0.1429,
          "sogPercentile": 0.982,
          "goalsPercentile": 0.8964,
          "sogLeagueAvg": 5.1256,
          "goalsLeagueAvg": 0.9596
        },
        "long": {
          "shotsOnGoal": 1,
          "goals": 0,
          "shootingPctg": 0.0,
          "sogPercentile": 0.3964,
          "goalsPercentile": 0.0,
          "sogLeagueAvg": 1.426,
          "goalsLeagueAvg": 0.0628
        },
        "mid": {
          "shotsOnGoal": 11,
          "goals": 2,
          "shootingPctg": 0.1818,
          "sogPercentile": 0.8829,
          "goalsPercentile": 0.8964,
          "sogLeagueAvg": 4.6099,
          "goalsLeagueAvg": 0.4978
        }
      }
    },
    "l5": null,
    "l10": null,
    "l20": null
  }
}