{
  "playerId": 8484144,
  "playerName": "Connor Bedard",
  "team": "HOME",
  "season": 2025,
  "totalGames": 67,
  "lastUpdated": "2026-06-12T12:55:37.810177",
  "szn": {
    "slot": {
      "shotsOnGoal": 87,
      "goals": 9,
      "attempts": 131,
      "xGoals": 7.14
    },
    "low": {
      "shotsOnGoal": 81,
      "goals": 18,
      "attempts": 109,
      "xGoals": 13.91
    },
    "lowLeft": {
      "shotsOnGoal": 32,
      "goals": 2,
      "attempts": 54,
      "xGoals": 3.38
    },
    "lowRight": {
      "shotsOnGoal": 19,
      "goals": 1,
      "attempts": 35,
      "xGoals": 1.51
    },
    "point": {
      "shotsOnGoal": 1,
      "goals": 0,
      "attempts": 1,
      "xGoals": 0.05
    },
    "left": {
      "shotsOnGoal": 4,
      "goals": 0,
      "attempts": 4,
      "xGoals": 0.03
    },
    "right": {
      "shotsOnGoal": 2,
      "goals": 0,
      "attempts": 2,
      "xGoals": 0.01
    },
    "total": {
      "shotsOnGoal": 226,
      "goals": 30,
      "attempts": 336,
      "xGoals": 26.03
    }
  },
  "l5": {
    "slot": {
      "shotsOnGoal": 8,
      "goals": 0,
      "attempts": 14,
      "xGoals": 0.75
    },
    "low": {
      "shotsOnGoal": 4,
      "goals": 0,
      "attempts": 7,
      "xGoals": 0.53
    },
    "lowLeft": {
      "shotsOnGoal": 3,
      "goals": 0,
      "attempts": 3,
      "xGoals": 0.25
    },
    "lowRight": {
      "shotsOnGoal": 1,
      "goals": 0,
      "attempts": 1,
      "xGoals": 0.01
    },
    "point": {
      "shotsOnGoal": 0,
      "goals": 0,
      "attempts": 0,
      "xGoals": 0.0
    },
    "left": {
      "shotsOnGoal": 0,
      "goals": 0,
      "attempts": 0,
      "xGoals": 0.0
    },
    "right": {
      "shotsOnGoal": 0,
      "goals": 0,
      "attempts": 0,
      "xGoals": 0.0
    },
    "total": {
      "shotsOnGoal": 16,
      "goals": 0,
      "attempts": 25,
      "xGoals": 1.53
    }
  },
  "l10": {
    "slot": {
      "shotsOnGoal": 18,
      "goals": 0,
      "attempts": 25,
      "xGoals": 1.33
    },
    "low": {
      "shotsOnGoal": 8,
      "goals": 1,
      "attempts": 13,
      "xGoals": 1.08
    },
    "lowLeft": {
      "shotsOnGoal": 6,
      "goals": 0,
      "attempts": 8,
      "xGoals": 0.35
    },
    "lowRight": {
      "shotsOnGoal": 2,
      "goals": 0,
      "attempts": 2,
      "xGoals": 0.02
    },
    "point": {
      "shotsOnGoal": 1,
      "goals": 0,
      "attempts": 1,
      "xGoals": 0.05
    },
    "left": {
      "shotsOnGoal": 0,
      "goals": 0,
      "attempts": 0,
      "xGoals": 0.0
    },
    "right": {
      "shotsOnGoal": 0,
      "goals": 0,
      "attempts": 0,
      "xGoals": 0.0
    },
    "total": {
      "shotsOnGoal": 35,
      "goals": 1,
      "attempts": 49,
      "xGoals": 2.84
    }
  },
  "l20": {
    "slot": {
      "shotsOnGoal": 33,
      "goals": 1,
      "attempts": 52,
      "xGoals": 2.63
    },
    "low": {
      "shotsOnGoal": 21,
      "goals": 4,
      "attempts": 33,
      "xGoals": 2.97
    },
    "lowLeft": {
      "shotsOnGoal": 7,
      "goals": 0,
      "attempts": 11,
      "xGoals": 0.42
    },
    "lowRight": {
      "shotsOnGoal": 4,
      "goals": 0,
      "attempts": 6,
      "xGoals": 0.11
    },
    "point": {
      "shotsOnGoal": 1,
      "goals": 0,
      "attempts": 1,
      "xGoals": 0.05
    },
    "left": {
      "shotsOnGoal": 1,
      "goals": 0,
      "attempts": 1,
      "xGoals": 0.01
    },
    "right": {
      "shotsOnGoal": 1,
      "goals": 0,
      "attempts": 1,
      "xGoals": 0.01
    },
    "total": {
      "shotsOnGoal": 68,
      "goals": 5,
      "attempts": 105,
      "xGoals": 6.19
    }
  }
}