{
  "playerId": 8482747,
  "playerName": "Brennan Othmann",
  "team": "AWAY",
  "season": 2025,
  "totalGames": 14,
  "lastUpdated": "2026-06-07T19:59:26.529111",
  "szn": {
    "slot": {
      "shotsOnGoal": 5,
      "goals": 0,
      "attempts": 8,
      "xGoals": 0.56
    },
    "low": {
      "shotsOnGoal": 8,
      "goals": 2,
      "attempts": 10,
      "xGoals": 1.42
    },
    "lowLeft": {
      "shotsOnGoal": 1,
      "goals": 0,
      "attempts": 1,
      "xGoals": 0.01
    },
    "lowRight": {
      "shotsOnGoal": 1,
      "goals": 0,
      "attempts": 4,
      "xGoals": 0.06
    },
    "point": {
      "shotsOnGoal": 0,
      "goals": 0,
      "attempts": 0,
      "xGoals": 0.0
    },
    "left": {
      "shotsOnGoal": 0,
      "goals": 0,
      "attempts": 0,
      "xGoals": 0.0
    },
    "right": {
      "shotsOnGoal": 0,
      "goals": 0,
      "attempts": 0,
      "xGoals": 0.0
    },
    "total": {
      "shotsOnGoal": 15,
      "goals": 2,
      "attempts": 23,
      "xGoals": 2.05
    }
  },
  "l5": {
    "slot": {
      "shotsOnGoal": 2,
      "goals": 0,
      "attempts": 3,
      "xGoals": 0.12
    },
    "low": {
      "shotsOnGoal": 3,
      "goals": 1,
      "attempts": 3,
      "xGoals": 0.69
    },
    "lowLeft": {
      "shotsOnGoal": 1,
      "goals": 0,
      "attempts": 1,
      "xGoals": 0.01
    },
    "lowRight": {
      "shotsOnGoal": 0,
      "goals": 0,
      "attempts": 1,
      "xGoals": 0.02
    },
    "point": {
      "shotsOnGoal": 0,
      "goals": 0,
      "attempts": 0,
      "xGoals": 0.0
    },
    "left": {
      "shotsOnGoal": 0,
      "goals": 0,
      "attempts": 0,
      "xGoals": 0.0
    },
    "right": {
      "shotsOnGoal": 0,
      "goals": 0,
      "attempts": 0,
      "xGoals": 0.0
    },
    "total": {
      "shotsOnGoal": 6,
      "goals": 1,
      "attempts": 8,
      "xGoals": 0.84
    }
  },
  "l10": {
    "slot": {
      "shotsOnGoal": 4,
      "goals": 0,
      "attempts": 6,
      "xGoals": 0.49
    },
    "low": {
      "shotsOnGoal": 6,
      "goals": 2,
      "attempts": 7,
      "xGoals": 1.05
    },
    "lowLeft": {
      "shotsOnGoal": 1,
      "goals": 0,
      "attempts": 1,
      "xGoals": 0.01
    },
    "lowRight": {
      "shotsOnGoal": 0,
      "goals": 0,
      "attempts": 2,
      "xGoals": 0.02
    },
    "point": {
      "shotsOnGoal": 0,
      "goals": 0,
      "attempts": 0,
      "xGoals": 0.0
    },
    "left": {
      "shotsOnGoal": 0,
      "goals": 0,
      "attempts": 0,
      "xGoals": 0.0
    },
    "right": {
      "shotsOnGoal": 0,
      "goals": 0,
      "attempts": 0,
      "xGoals": 0.0
    },
    "total": {
      "shotsOnGoal": 11,
      "goals": 2,
      "attempts": 16,
      "xGoals": 1.57
    }
  },
  "l20": {
    "slot": {
      "shotsOnGoal": 5,
      "goals": 0,
      "attempts": 8,
      "xGoals": 0.56
    },
    "low": {
      "shotsOnGoal": 8,
      "goals": 2,
      "attempts": 10,
      "xGoals": 1.42
    },
    "lowLeft": {
      "shotsOnGoal": 1,
      "goals": 0,
      "attempts": 1,
      "xGoals": 0.01
    },
    "lowRight": {
      "shotsOnGoal": 1,
      "goals": 0,
      "attempts": 4,
      "xGoals": 0.06
    },
    "point": {
      "shotsOnGoal": 0,
      "goals": 0,
      "attempts": 0,
      "xGoals": 0.0
    },
    "left": {
      "shotsOnGoal": 0,
      "goals": 0,
      "attempts": 0,
      "xGoals": 0.0
    },
    "right": {
      "shotsOnGoal": 0,
      "goals": 0,
      "attempts": 0,
      "xGoals": 0.0
    },
    "total": {
      "shotsOnGoal": 15,
      "goals": 2,
      "attempts": 23,
      "xGoals": 2.05
    }
  }
}