{
  "playerId": 8477446,
  "playerName": "Michael McCarron",
  "team": "AWAY",
  "season": 2025,
  "lastUpdated": "2026-06-30T12:12:15.424990",
  "reg": {
    "totalGames": 79,
    "szn": {
      "slot": {
        "shotsOnGoal": 50,
        "goals": 7,
        "shootingPctg": 0.14,
        "sogPercentile": 0.8071,
        "goalsPercentile": 0.6327
      },
      "highSlot": {
        "shotsOnGoal": 4,
        "goals": 1,
        "shootingPctg": 0.25,
        "sogPercentile": 0.3502,
        "goalsPercentile": 0.4316
      },
      "leftCircle": {
        "shotsOnGoal": 6,
        "goals": 0,
        "shootingPctg": 0.0,
        "sogPercentile": 0.4756,
        "goalsPercentile": 0.0
      },
      "rightCircle": {
        "shotsOnGoal": 6,
        "goals": 0,
        "shootingPctg": 0.0,
        "sogPercentile": 0.4528,
        "goalsPercentile": 0.0
      },
      "cornerLeft": {
        "shotsOnGoal": 5,
        "goals": 0,
        "shootingPctg": 0.0,
        "sogPercentile": 0.4039,
        "goalsPercentile": 0.0
      },
      "cornerRight": {
        "shotsOnGoal": 3,
        "goals": 0,
        "shootingPctg": 0.0,
        "sogPercentile": 0.6963,
        "goalsPercentile": 0.0
      },
      "pointLeft": {
        "shotsOnGoal": 4,
        "goals": 0,
        "shootingPctg": 0.0,
        "sogPercentile": 0.7215,
        "goalsPercentile": 0.0
      },
      "pointRight": {
        "shotsOnGoal": 4,
        "goals": 0,
        "shootingPctg": 0.0,
        "sogPercentile": 0.7345,
        "goalsPercentile": 0.0
      },
      "pointCenter": {
        "shotsOnGoal": 2,
        "goals": 0,
        "shootingPctg": 0.0,
        "sogPercentile": 0.4886,
        "goalsPercentile": 0.0
      },
      "total": {
        "shotsOnGoal": 84,
        "goals": 8,
        "shootingPctg": 0.0952
      },
      "totals": {
        "all": {
          "shotsOnGoal": 109,
          "goals": 8,
          "shootingPctg": 0.0734,
          "sogPercentile": 0.6515,
          "goalsPercentile": 0.4805,
          "sogLeagueAvg": 85.9138,
          "goalsLeagueAvg": 11.1545
        },
        "high": {
          "shotsOnGoal": 50,
          "goals": 7,
          "shootingPctg": 0.14,
          "sogPercentile": 0.7476,
          "goalsPercentile": 0.5912,
          "sogLeagueAvg": 31.6244,
          "goalsLeagueAvg": 6.1935
        },
        "long": {
          "shotsOnGoal": 10,
          "goals": 0,
          "shootingPctg": 0.0,
          "sogPercentile": 0.6889,
          "goalsPercentile": 0.0,
          "sogLeagueAvg": 8.0081,
          "goalsLeagueAvg": 0.3106
        },
        "mid": {
          "shotsOnGoal": 16,
          "goals": 1,
          "shootingPctg": 0.0625,
          "sogPercentile": 0.4202,
          "goalsPercentile": 0.2964,
          "sogLeagueAvg": 27.2195,
          "goalsLeagueAvg": 3.3008
        }
      }
    },
    "l5": null,
    "l10": null,
    "l20": null
  },
  "playoffs": {
    "totalGames": 11,
    "szn": {
      "slot": {
        "shotsOnGoal": 1,
        "goals": 1,
        "shootingPctg": 1.0,
        "sogPercentile": 0.0897,
        "goalsPercentile": 0.2937
      },
      "highSlot": {
        "shotsOnGoal": 1,
        "goals": 0,
        "shootingPctg": 0.0,
        "sogPercentile": 0.3991,
        "goalsPercentile": 0.0
      },
      "leftCircle": {
        "shotsOnGoal": 0,
        "goals": 0,
        "shootingPctg": 0.0,
        "sogPercentile": 0.0,
        "goalsPercentile": 0.0
      },
      "rightCircle": {
        "shotsOnGoal": 2,
        "goals": 1,
        "shootingPctg": 0.5,
        "sogPercentile": 0.6323,
        "goalsPercentile": 0.8744
      },
      "cornerLeft": {
        "shotsOnGoal": 2,
        "goals": 0,
        "shootingPctg": 0.0,
        "sogPercentile": 0.4417,
        "goalsPercentile": 0.0
      },
      "cornerRight": {
        "shotsOnGoal": 1,
        "goals": 0,
        "shootingPctg": 0.0,
        "sogPercentile": 0.482,
        "goalsPercentile": 0.0
      },
      "pointLeft": {
        "shotsOnGoal": 1,
        "goals": 0,
        "shootingPctg": 0.0,
        "sogPercentile": 0.6502,
        "goalsPercentile": 0.0
      },
      "pointRight": {
        "shotsOnGoal": 3,
        "goals": 0,
        "shootingPctg": 0.0,
        "sogPercentile": 0.9552,
        "goalsPercentile": 0.0
      },
      "pointCenter": {
        "shotsOnGoal": 1,
        "goals": 0,
        "shootingPctg": 0.0,
        "sogPercentile": 0.7175,
        "goalsPercentile": 0.0
      },
      "total": {
        "shotsOnGoal": 12,
        "goals": 2,
        "shootingPctg": 0.1667
      },
      "totals": {
        "all": {
          "shotsOnGoal": 14,
          "goals": 2,
          "shootingPctg": 0.1429,
          "sogPercentile": 0.5874,
          "goalsPercentile": 0.565,
          "sogLeagueAvg": 15.1295,
          "goalsLeagueAvg": 1.8393
        },
        "high": {
          "shotsOnGoal": 1,
          "goals": 1,
          "shootingPctg": 1.0,
          "sogPercentile": 0.148,
          "goalsPercentile": 0.5202,
          "sogLeagueAvg": 5.1518,
          "goalsLeagueAvg": 0.9554
        },
        "long": {
          "shotsOnGoal": 5,
          "goals": 0,
          "shootingPctg": 0.0,
          "sogPercentile": 0.9327,
          "goalsPercentile": 0.0,
          "sogLeagueAvg": 1.4554,
          "goalsLeagueAvg": 0.067
        },
        "mid": {
          "shotsOnGoal": 3,
          "goals": 1,
          "shootingPctg": 0.3333,
          "sogPercentile": 0.4215,
          "goalsPercentile": 0.6771,
          "sogLeagueAvg": 4.6384,
          "goalsLeagueAvg": 0.5045
        }
      }
    },
    "l5": null,
    "l10": null,
    "l20": null
  }
}