{
  "playerId": 8478057,
  "playerName": "Dakota Joshua",
  "team": "HOME",
  "season": 2025,
  "lastUpdated": "2026-06-30T12:12:06.974477",
  "reg": {
    "totalGames": 55,
    "szn": {
      "slot": {
        "shotsOnGoal": 31,
        "goals": 5,
        "shootingPctg": 0.1613,
        "sogPercentile": 0.5684,
        "goalsPercentile": 0.2687
      },
      "highSlot": {
        "shotsOnGoal": 4,
        "goals": 2,
        "shootingPctg": 0.5,
        "sogPercentile": 0.3502,
        "goalsPercentile": 0.6661
      },
      "leftCircle": {
        "shotsOnGoal": 4,
        "goals": 2,
        "shootingPctg": 0.5,
        "sogPercentile": 0.3518,
        "goalsPercentile": 0.7769
      },
      "rightCircle": {
        "shotsOnGoal": 0,
        "goals": 0,
        "shootingPctg": 0.0,
        "sogPercentile": 0.0,
        "goalsPercentile": 0.0
      },
      "cornerLeft": {
        "shotsOnGoal": 1,
        "goals": 0,
        "shootingPctg": 0.0,
        "sogPercentile": 0.1539,
        "goalsPercentile": 0.0
      },
      "cornerRight": {
        "shotsOnGoal": 3,
        "goals": 0,
        "shootingPctg": 0.0,
        "sogPercentile": 0.3151,
        "goalsPercentile": 0.0
      },
      "pointLeft": {
        "shotsOnGoal": 2,
        "goals": 0,
        "shootingPctg": 0.0,
        "sogPercentile": 0.4691,
        "goalsPercentile": 0.0
      },
      "pointRight": {
        "shotsOnGoal": 1,
        "goals": 0,
        "shootingPctg": 0.0,
        "sogPercentile": 0.3322,
        "goalsPercentile": 0.0
      },
      "pointCenter": {
        "shotsOnGoal": 1,
        "goals": 0,
        "shootingPctg": 0.0,
        "sogPercentile": 0.3046,
        "goalsPercentile": 0.0
      },
      "total": {
        "shotsOnGoal": 47,
        "goals": 9,
        "shootingPctg": 0.1915
      },
      "totals": {
        "all": {
          "shotsOnGoal": 52,
          "goals": 10,
          "shootingPctg": 0.1923,
          "sogPercentile": 0.3876,
          "goalsPercentile": 0.5423,
          "sogLeagueAvg": 85.9138,
          "goalsLeagueAvg": 11.1545
        },
        "high": {
          "shotsOnGoal": 31,
          "goals": 5,
          "shootingPctg": 0.1613,
          "sogPercentile": 0.5293,
          "goalsPercentile": 0.4902,
          "sogLeagueAvg": 31.6244,
          "goalsLeagueAvg": 6.1935
        },
        "long": {
          "shotsOnGoal": 4,
          "goals": 0,
          "shootingPctg": 0.0,
          "sogPercentile": 0.3697,
          "goalsPercentile": 0.0,
          "sogLeagueAvg": 8.0081,
          "goalsLeagueAvg": 0.3106
        },
        "mid": {
          "shotsOnGoal": 8,
          "goals": 4,
          "shootingPctg": 0.5,
          "sogPercentile": 0.2932,
          "goalsPercentile": 0.6482,
          "sogLeagueAvg": 27.2195,
          "goalsLeagueAvg": 3.3008
        }
      }
    },
    "l5": null,
    "l10": null,
    "l20": null
  },
  "playoffs": null
}