{
  "playerId": 8480078,
  "playerName": "Filip Chytil",
  "team": "AWAY",
  "season": 2025,
  "lastUpdated": "2026-06-16T15:12:28.243495",
  "reg": {
    "totalGames": 12,
    "szn": {
      "slot": {
        "shotsOnGoal": 6,
        "goals": 0,
        "attempts": 7,
        "xGoals": 0.5
      },
      "low": {
        "shotsOnGoal": 13,
        "goals": 3,
        "attempts": 20,
        "xGoals": 2.45
      },
      "lowLeft": {
        "shotsOnGoal": 3,
        "goals": 0,
        "attempts": 3,
        "xGoals": 0.08
      },
      "lowRight": {
        "shotsOnGoal": 2,
        "goals": 0,
        "attempts": 4,
        "xGoals": 0.08
      },
      "point": {
        "shotsOnGoal": 0,
        "goals": 0,
        "attempts": 1,
        "xGoals": 0.07
      },
      "left": {
        "shotsOnGoal": 0,
        "goals": 0,
        "attempts": 0,
        "xGoals": 0.0
      },
      "right": {
        "shotsOnGoal": 0,
        "goals": 0,
        "attempts": 0,
        "xGoals": 0.0
      },
      "total": {
        "shotsOnGoal": 24,
        "goals": 3,
        "attempts": 35,
        "xGoals": 3.17
      }
    },
    "l5": {
      "slot": {
        "shotsOnGoal": 3,
        "goals": 0,
        "attempts": 3,
        "xGoals": 0.21
      },
      "low": {
        "shotsOnGoal": 3,
        "goals": 0,
        "attempts": 6,
        "xGoals": 0.52
      },
      "lowLeft": {
        "shotsOnGoal": 1,
        "goals": 0,
        "attempts": 1,
        "xGoals": 0.02
      },
      "lowRight": {
        "shotsOnGoal": 0,
        "goals": 0,
        "attempts": 1,
        "xGoals": 0.01
      },
      "point": {
        "shotsOnGoal": 0,
        "goals": 0,
        "attempts": 1,
        "xGoals": 0.07
      },
      "left": {
        "shotsOnGoal": 0,
        "goals": 0,
        "attempts": 0,
        "xGoals": 0.0
      },
      "right": {
        "shotsOnGoal": 0,
        "goals": 0,
        "attempts": 0,
        "xGoals": 0.0
      },
      "total": {
        "shotsOnGoal": 7,
        "goals": 0,
        "attempts": 12,
        "xGoals": 0.82
      }
    },
    "l10": {
      "slot": {
        "shotsOnGoal": 3,
        "goals": 0,
        "attempts": 3,
        "xGoals": 0.21
      },
      "low": {
        "shotsOnGoal": 11,
        "goals": 1,
        "attempts": 17,
        "xGoals": 1.9
      },
      "lowLeft": {
        "shotsOnGoal": 3,
        "goals": 0,
        "attempts": 3,
        "xGoals": 0.08
      },
      "lowRight": {
        "shotsOnGoal": 1,
        "goals": 0,
        "attempts": 3,
        "xGoals": 0.04
      },
      "point": {
        "shotsOnGoal": 0,
        "goals": 0,
        "attempts": 1,
        "xGoals": 0.07
      },
      "left": {
        "shotsOnGoal": 0,
        "goals": 0,
        "attempts": 0,
        "xGoals": 0.0
      },
      "right": {
        "shotsOnGoal": 0,
        "goals": 0,
        "attempts": 0,
        "xGoals": 0.0
      },
      "total": {
        "shotsOnGoal": 18,
        "goals": 1,
        "attempts": 27,
        "xGoals": 2.29
      }
    },
    "l20": {
      "slot": {
        "shotsOnGoal": 6,
        "goals": 0,
        "attempts": 7,
        "xGoals": 0.5
      },
      "low": {
        "shotsOnGoal": 13,
        "goals": 3,
        "attempts": 20,
        "xGoals": 2.45
      },
      "lowLeft": {
        "shotsOnGoal": 3,
        "goals": 0,
        "attempts": 3,
        "xGoals": 0.08
      },
      "lowRight": {
        "shotsOnGoal": 2,
        "goals": 0,
        "attempts": 4,
        "xGoals": 0.08
      },
      "point": {
        "shotsOnGoal": 0,
        "goals": 0,
        "attempts": 1,
        "xGoals": 0.07
      },
      "left": {
        "shotsOnGoal": 0,
        "goals": 0,
        "attempts": 0,
        "xGoals": 0.0
      },
      "right": {
        "shotsOnGoal": 0,
        "goals": 0,
        "attempts": 0,
        "xGoals": 0.0
      },
      "total": {
        "shotsOnGoal": 24,
        "goals": 3,
        "attempts": 35,
        "xGoals": 3.17
      }
    }
  },
  "playoffs": null
}