{
  "playerId": 8478498,
  "playerName": "Jake DeBrusk",
  "team": "AWAY",
  "season": 2025,
  "totalGames": 79,
  "lastUpdated": "2026-06-12T12:57:08.532982",
  "szn": {
    "slot": {
      "shotsOnGoal": 39,
      "goals": 1,
      "attempts": 62,
      "xGoals": 2.67
    },
    "low": {
      "shotsOnGoal": 134,
      "goals": 22,
      "attempts": 195,
      "xGoals": 30.74
    },
    "lowLeft": {
      "shotsOnGoal": 13,
      "goals": 0,
      "attempts": 21,
      "xGoals": 0.36
    },
    "lowRight": {
      "shotsOnGoal": 14,
      "goals": 0,
      "attempts": 22,
      "xGoals": 0.5
    },
    "point": {
      "shotsOnGoal": 8,
      "goals": 0,
      "attempts": 9,
      "xGoals": 0.16
    },
    "left": {
      "shotsOnGoal": 7,
      "goals": 0,
      "attempts": 7,
      "xGoals": 0.04
    },
    "right": {
      "shotsOnGoal": 3,
      "goals": 0,
      "attempts": 4,
      "xGoals": 0.04
    },
    "total": {
      "shotsOnGoal": 218,
      "goals": 23,
      "attempts": 320,
      "xGoals": 34.52
    }
  },
  "l5": {
    "slot": {
      "shotsOnGoal": 4,
      "goals": 0,
      "attempts": 6,
      "xGoals": 0.15
    },
    "low": {
      "shotsOnGoal": 14,
      "goals": 4,
      "attempts": 15,
      "xGoals": 2.98
    },
    "lowLeft": {
      "shotsOnGoal": 0,
      "goals": 0,
      "attempts": 0,
      "xGoals": 0.0
    },
    "lowRight": {
      "shotsOnGoal": 1,
      "goals": 0,
      "attempts": 3,
      "xGoals": 0.08
    },
    "point": {
      "shotsOnGoal": 1,
      "goals": 0,
      "attempts": 1,
      "xGoals": 0.01
    },
    "left": {
      "shotsOnGoal": 1,
      "goals": 0,
      "attempts": 1,
      "xGoals": 0.01
    },
    "right": {
      "shotsOnGoal": 0,
      "goals": 0,
      "attempts": 0,
      "xGoals": 0.0
    },
    "total": {
      "shotsOnGoal": 21,
      "goals": 4,
      "attempts": 26,
      "xGoals": 3.22
    }
  },
  "l10": {
    "slot": {
      "shotsOnGoal": 6,
      "goals": 0,
      "attempts": 8,
      "xGoals": 0.2
    },
    "low": {
      "shotsOnGoal": 24,
      "goals": 7,
      "attempts": 28,
      "xGoals": 5.39
    },
    "lowLeft": {
      "shotsOnGoal": 0,
      "goals": 0,
      "attempts": 1,
      "xGoals": 0.01
    },
    "lowRight": {
      "shotsOnGoal": 2,
      "goals": 0,
      "attempts": 4,
      "xGoals": 0.1
    },
    "point": {
      "shotsOnGoal": 1,
      "goals": 0,
      "attempts": 1,
      "xGoals": 0.01
    },
    "left": {
      "shotsOnGoal": 1,
      "goals": 0,
      "attempts": 1,
      "xGoals": 0.01
    },
    "right": {
      "shotsOnGoal": 0,
      "goals": 0,
      "attempts": 0,
      "xGoals": 0.0
    },
    "total": {
      "shotsOnGoal": 34,
      "goals": 7,
      "attempts": 43,
      "xGoals": 5.7
    }
  },
  "l20": {
    "slot": {
      "shotsOnGoal": 13,
      "goals": 0,
      "attempts": 18,
      "xGoals": 0.68
    },
    "low": {
      "shotsOnGoal": 33,
      "goals": 9,
      "attempts": 41,
      "xGoals": 7.45
    },
    "lowLeft": {
      "shotsOnGoal": 0,
      "goals": 0,
      "attempts": 4,
      "xGoals": 0.05
    },
    "lowRight": {
      "shotsOnGoal": 4,
      "goals": 0,
      "attempts": 7,
      "xGoals": 0.19
    },
    "point": {
      "shotsOnGoal": 2,
      "goals": 0,
      "attempts": 2,
      "xGoals": 0.01
    },
    "left": {
      "shotsOnGoal": 2,
      "goals": 0,
      "attempts": 2,
      "xGoals": 0.02
    },
    "right": {
      "shotsOnGoal": 1,
      "goals": 0,
      "attempts": 2,
      "xGoals": 0.03
    },
    "total": {
      "shotsOnGoal": 55,
      "goals": 9,
      "attempts": 76,
      "xGoals": 8.43
    }
  }
}