{
  "playerId": 8479316,
  "playerName": "Luke Kunin",
  "team": "HOME",
  "season": 2025,
  "lastUpdated": "2026-06-16T15:12:13.924644",
  "reg": {
    "totalGames": 37,
    "szn": {
      "slot": {
        "shotsOnGoal": 15,
        "goals": 2,
        "attempts": 20,
        "xGoals": 1.18
      },
      "low": {
        "shotsOnGoal": 21,
        "goals": 2,
        "attempts": 32,
        "xGoals": 4.53
      },
      "lowLeft": {
        "shotsOnGoal": 3,
        "goals": 0,
        "attempts": 5,
        "xGoals": 0.09
      },
      "lowRight": {
        "shotsOnGoal": 6,
        "goals": 0,
        "attempts": 9,
        "xGoals": 0.17
      },
      "point": {
        "shotsOnGoal": 1,
        "goals": 0,
        "attempts": 1,
        "xGoals": 0.01
      },
      "left": {
        "shotsOnGoal": 2,
        "goals": 0,
        "attempts": 2,
        "xGoals": 0.03
      },
      "right": {
        "shotsOnGoal": 0,
        "goals": 0,
        "attempts": 2,
        "xGoals": 0.02
      },
      "total": {
        "shotsOnGoal": 48,
        "goals": 4,
        "attempts": 71,
        "xGoals": 6.03
      }
    },
    "l5": {
      "slot": {
        "shotsOnGoal": 3,
        "goals": 1,
        "attempts": 3,
        "xGoals": 0.12
      },
      "low": {
        "shotsOnGoal": 4,
        "goals": 1,
        "attempts": 7,
        "xGoals": 0.89
      },
      "lowLeft": {
        "shotsOnGoal": 1,
        "goals": 0,
        "attempts": 1,
        "xGoals": 0.01
      },
      "lowRight": {
        "shotsOnGoal": 0,
        "goals": 0,
        "attempts": 0,
        "xGoals": 0.0
      },
      "point": {
        "shotsOnGoal": 0,
        "goals": 0,
        "attempts": 0,
        "xGoals": 0.0
      },
      "left": {
        "shotsOnGoal": 0,
        "goals": 0,
        "attempts": 0,
        "xGoals": 0.0
      },
      "right": {
        "shotsOnGoal": 0,
        "goals": 0,
        "attempts": 0,
        "xGoals": 0.0
      },
      "total": {
        "shotsOnGoal": 8,
        "goals": 2,
        "attempts": 11,
        "xGoals": 1.02
      }
    },
    "l10": {
      "slot": {
        "shotsOnGoal": 3,
        "goals": 1,
        "attempts": 5,
        "xGoals": 0.23
      },
      "low": {
        "shotsOnGoal": 10,
        "goals": 1,
        "attempts": 14,
        "xGoals": 1.82
      },
      "lowLeft": {
        "shotsOnGoal": 1,
        "goals": 0,
        "attempts": 1,
        "xGoals": 0.01
      },
      "lowRight": {
        "shotsOnGoal": 1,
        "goals": 0,
        "attempts": 2,
        "xGoals": 0.03
      },
      "point": {
        "shotsOnGoal": 0,
        "goals": 0,
        "attempts": 0,
        "xGoals": 0.0
      },
      "left": {
        "shotsOnGoal": 1,
        "goals": 0,
        "attempts": 1,
        "xGoals": 0.02
      },
      "right": {
        "shotsOnGoal": 0,
        "goals": 0,
        "attempts": 1,
        "xGoals": 0.01
      },
      "total": {
        "shotsOnGoal": 16,
        "goals": 2,
        "attempts": 24,
        "xGoals": 2.11
      }
    },
    "l20": {
      "slot": {
        "shotsOnGoal": 6,
        "goals": 1,
        "attempts": 9,
        "xGoals": 0.49
      },
      "low": {
        "shotsOnGoal": 14,
        "goals": 1,
        "attempts": 20,
        "xGoals": 2.74
      },
      "lowLeft": {
        "shotsOnGoal": 2,
        "goals": 0,
        "attempts": 3,
        "xGoals": 0.04
      },
      "lowRight": {
        "shotsOnGoal": 4,
        "goals": 0,
        "attempts": 5,
        "xGoals": 0.07
      },
      "point": {
        "shotsOnGoal": 1,
        "goals": 0,
        "attempts": 1,
        "xGoals": 0.01
      },
      "left": {
        "shotsOnGoal": 1,
        "goals": 0,
        "attempts": 1,
        "xGoals": 0.02
      },
      "right": {
        "shotsOnGoal": 0,
        "goals": 0,
        "attempts": 2,
        "xGoals": 0.02
      },
      "total": {
        "shotsOnGoal": 28,
        "goals": 2,
        "attempts": 41,
        "xGoals": 3.4
      }
    }
  },
  "playoffs": null
}