{
  "playerId": 8480870,
  "playerName": "Bo Groulx",
  "team": "HOME",
  "season": 2025,
  "lastUpdated": "2026-06-30T12:12:29.055748",
  "reg": {
    "totalGames": 13,
    "szn": {
      "slot": {
        "shotsOnGoal": 4,
        "goals": 0,
        "shootingPctg": 0.0,
        "sogPercentile": 0.0977,
        "goalsPercentile": 0.0
      },
      "highSlot": {
        "shotsOnGoal": 4,
        "goals": 2,
        "shootingPctg": 0.5,
        "sogPercentile": 0.3502,
        "goalsPercentile": 0.6661
      },
      "leftCircle": {
        "shotsOnGoal": 4,
        "goals": 1,
        "shootingPctg": 0.25,
        "sogPercentile": 0.3518,
        "goalsPercentile": 0.57
      },
      "rightCircle": {
        "shotsOnGoal": 1,
        "goals": 0,
        "shootingPctg": 0.0,
        "sogPercentile": 0.1629,
        "goalsPercentile": 0.0
      },
      "cornerLeft": {
        "shotsOnGoal": 0,
        "goals": 0,
        "shootingPctg": 0.0,
        "sogPercentile": 0.0,
        "goalsPercentile": 0.0
      },
      "cornerRight": {
        "shotsOnGoal": 0,
        "goals": 0,
        "shootingPctg": 0.0,
        "sogPercentile": 0.0,
        "goalsPercentile": 0.0
      },
      "pointLeft": {
        "shotsOnGoal": 0,
        "goals": 0,
        "shootingPctg": 0.0,
        "sogPercentile": 0.0,
        "goalsPercentile": 0.0
      },
      "pointRight": {
        "shotsOnGoal": 0,
        "goals": 0,
        "shootingPctg": 0.0,
        "sogPercentile": 0.0,
        "goalsPercentile": 0.0
      },
      "pointCenter": {
        "shotsOnGoal": 0,
        "goals": 0,
        "shootingPctg": 0.0,
        "sogPercentile": 0.0,
        "goalsPercentile": 0.0
      },
      "total": {
        "shotsOnGoal": 13,
        "goals": 3,
        "shootingPctg": 0.2308
      },
      "totals": {
        "all": {
          "shotsOnGoal": 15,
          "goals": 3,
          "shootingPctg": 0.2,
          "sogPercentile": 0.2101,
          "goalsPercentile": 0.2834,
          "sogLeagueAvg": 85.9138,
          "goalsLeagueAvg": 11.1545
        },
        "high": {
          "shotsOnGoal": 4,
          "goals": 0,
          "shootingPctg": 0.0,
          "sogPercentile": 0.1906,
          "goalsPercentile": 0.0,
          "sogLeagueAvg": 31.6244,
          "goalsLeagueAvg": 6.1935
        },
        "long": {
          "shotsOnGoal": 0,
          "goals": 0,
          "shootingPctg": 0.0,
          "sogPercentile": 0.0,
          "goalsPercentile": 0.0,
          "sogLeagueAvg": 8.0081,
          "goalsLeagueAvg": 0.3106
        },
        "mid": {
          "shotsOnGoal": 9,
          "goals": 3,
          "shootingPctg": 0.3333,
          "sogPercentile": 0.3143,
          "goalsPercentile": 0.557,
          "sogLeagueAvg": 27.2195,
          "goalsLeagueAvg": 3.3008
        }
      }
    },
    "l5": null,
    "l10": null,
    "l20": null
  },
  "playoffs": null
}