{
  "playerId": 8481237,
  "playerName": "Kyle MacLean",
  "team": "HOME",
  "season": 2025,
  "lastUpdated": "2026-06-25T12:23:54.026599",
  "reg": {
    "totalGames": 44,
    "szn": {
      "slot": {
        "shotsOnGoal": 6,
        "goals": 1,
        "attempts": 14,
        "xGoals": 0.94
      },
      "low": {
        "shotsOnGoal": 21,
        "goals": 1,
        "attempts": 39,
        "xGoals": 4.19
      },
      "lowLeft": {
        "shotsOnGoal": 6,
        "goals": 0,
        "attempts": 11,
        "xGoals": 0.26
      },
      "lowRight": {
        "shotsOnGoal": 7,
        "goals": 0,
        "attempts": 9,
        "xGoals": 0.18
      },
      "point": {
        "shotsOnGoal": 1,
        "goals": 0,
        "attempts": 1,
        "xGoals": 0.02
      },
      "left": {
        "shotsOnGoal": 1,
        "goals": 0,
        "attempts": 1,
        "xGoals": 0.01
      },
      "right": {
        "shotsOnGoal": 0,
        "goals": 0,
        "attempts": 2,
        "xGoals": 0.03
      },
      "total": {
        "shotsOnGoal": 42,
        "goals": 2,
        "attempts": 77,
        "xGoals": 5.62
      }
    },
    "l5": {
      "slot": {
        "shotsOnGoal": 0,
        "goals": 0,
        "attempts": 0,
        "xGoals": 0.0
      },
      "low": {
        "shotsOnGoal": 1,
        "goals": 0,
        "attempts": 6,
        "xGoals": 0.45
      },
      "lowLeft": {
        "shotsOnGoal": 0,
        "goals": 0,
        "attempts": 1,
        "xGoals": 0.02
      },
      "lowRight": {
        "shotsOnGoal": 1,
        "goals": 0,
        "attempts": 2,
        "xGoals": 0.06
      },
      "point": {
        "shotsOnGoal": 0,
        "goals": 0,
        "attempts": 0,
        "xGoals": 0.0
      },
      "left": {
        "shotsOnGoal": 0,
        "goals": 0,
        "attempts": 0,
        "xGoals": 0.0
      },
      "right": {
        "shotsOnGoal": 0,
        "goals": 0,
        "attempts": 0,
        "xGoals": 0.0
      },
      "total": {
        "shotsOnGoal": 2,
        "goals": 0,
        "attempts": 9,
        "xGoals": 0.52
      }
    },
    "l10": {
      "slot": {
        "shotsOnGoal": 1,
        "goals": 0,
        "attempts": 2,
        "xGoals": 0.15
      },
      "low": {
        "shotsOnGoal": 4,
        "goals": 0,
        "attempts": 12,
        "xGoals": 0.94
      },
      "lowLeft": {
        "shotsOnGoal": 0,
        "goals": 0,
        "attempts": 2,
        "xGoals": 0.06
      },
      "lowRight": {
        "shotsOnGoal": 2,
        "goals": 0,
        "attempts": 3,
        "xGoals": 0.06
      },
      "point": {
        "shotsOnGoal": 0,
        "goals": 0,
        "attempts": 0,
        "xGoals": 0.0
      },
      "left": {
        "shotsOnGoal": 0,
        "goals": 0,
        "attempts": 0,
        "xGoals": 0.0
      },
      "right": {
        "shotsOnGoal": 0,
        "goals": 0,
        "attempts": 0,
        "xGoals": 0.0
      },
      "total": {
        "shotsOnGoal": 7,
        "goals": 0,
        "attempts": 19,
        "xGoals": 1.22
      }
    },
    "l20": {
      "slot": {
        "shotsOnGoal": 2,
        "goals": 0,
        "attempts": 5,
        "xGoals": 0.35
      },
      "low": {
        "shotsOnGoal": 10,
        "goals": 0,
        "attempts": 23,
        "xGoals": 2.01
      },
      "lowLeft": {
        "shotsOnGoal": 1,
        "goals": 0,
        "attempts": 5,
        "xGoals": 0.12
      },
      "lowRight": {
        "shotsOnGoal": 2,
        "goals": 0,
        "attempts": 4,
        "xGoals": 0.07
      },
      "point": {
        "shotsOnGoal": 0,
        "goals": 0,
        "attempts": 0,
        "xGoals": 0.0
      },
      "left": {
        "shotsOnGoal": 0,
        "goals": 0,
        "attempts": 0,
        "xGoals": 0.0
      },
      "right": {
        "shotsOnGoal": 0,
        "goals": 0,
        "attempts": 1,
        "xGoals": 0.02
      },
      "total": {
        "shotsOnGoal": 15,
        "goals": 0,
        "attempts": 38,
        "xGoals": 2.57
      }
    }
  },
  "playoffs": null
}