{
  "playerId": 8481043,
  "playerName": "Cole Koepke",
  "team": "WPG",
  "position": "L",
  "season": 2026,
  "lastUpdated": "2026-06-30T23:49:19.722291",
  "reg": {
    "totalGames": 66,
    "szn": {
      "slot": {
        "shotsOnGoal": 23,
        "goals": 5,
        "shootingPctg": 0.2174,
        "sogPercentile": 0.3616,
        "goalsPercentile": 0.4991
      },
      "highSlot": {
        "shotsOnGoal": 8,
        "goals": 1,
        "shootingPctg": 0.125,
        "sogPercentile": 0.5456,
        "goalsPercentile": 0.4316
      },
      "leftCircle": {
        "shotsOnGoal": 16,
        "goals": 0,
        "shootingPctg": 0.0,
        "sogPercentile": 0.6662,
        "goalsPercentile": 0.0
      },
      "rightCircle": {
        "shotsOnGoal": 17,
        "goals": 1,
        "shootingPctg": 0.0588,
        "sogPercentile": 0.6946,
        "goalsPercentile": 0.2646
      },
      "cornerLeft": {
        "shotsOnGoal": 1,
        "goals": 0,
        "shootingPctg": 0.0,
        "sogPercentile": 0.1539,
        "goalsPercentile": 0.0
      },
      "cornerRight": {
        "shotsOnGoal": 3,
        "goals": 0,
        "shootingPctg": 0.0,
        "sogPercentile": 0.3151,
        "goalsPercentile": 0.0
      },
      "pointLeft": {
        "shotsOnGoal": 5,
        "goals": 0,
        "shootingPctg": 0.0,
        "sogPercentile": 0.7997,
        "goalsPercentile": 0.0
      },
      "pointRight": {
        "shotsOnGoal": 2,
        "goals": 0,
        "shootingPctg": 0.0,
        "sogPercentile": 0.5033,
        "goalsPercentile": 0.0
      },
      "pointCenter": {
        "shotsOnGoal": 4,
        "goals": 0,
        "shootingPctg": 0.0,
        "sogPercentile": 0.4536,
        "goalsPercentile": 0.0
      },
      "total": {
        "shotsOnGoal": 79,
        "goals": 7,
        "shootingPctg": 0.0886
      },
      "totals": {
        "all": {
          "shotsOnGoal": 86,
          "goals": 8,
          "shootingPctg": 0.093,
          "sogPercentile": 0.557,
          "goalsPercentile": 0.4805,
          "sogLeagueAvg": 85.9138,
          "goalsLeagueAvg": 11.1545
        },
        "high": {
          "shotsOnGoal": 23,
          "goals": 5,
          "shootingPctg": 0.2174,
          "sogPercentile": 0.4349,
          "goalsPercentile": 0.4902,
          "sogLeagueAvg": 31.6244,
          "goalsLeagueAvg": 6.1935
        },
        "long": {
          "shotsOnGoal": 10,
          "goals": 0,
          "shootingPctg": 0.0,
          "sogPercentile": 0.6889,
          "goalsPercentile": 0.0,
          "sogLeagueAvg": 8.0081,
          "goalsLeagueAvg": 0.3106
        },
        "mid": {
          "shotsOnGoal": 24,
          "goals": 2,
          "shootingPctg": 0.0833,
          "sogPercentile": 0.5586,
          "goalsPercentile": 0.4381,
          "sogLeagueAvg": 27.2195,
          "goalsLeagueAvg": 3.3008
        }
      }
    },
    "l5": null,
    "l10": null,
    "l20": null
  },
  "playoffs": null
}