{
  "playerId": 8484160,
  "playerName": "Nate Danielson",
  "team": "HOME",
  "season": 2025,
  "lastUpdated": "2026-06-30T12:12:25.584413",
  "reg": {
    "totalGames": 28,
    "szn": {
      "slot": {
        "shotsOnGoal": 8,
        "goals": 2,
        "shootingPctg": 0.25,
        "sogPercentile": 0.3045,
        "goalsPercentile": 0.1572
      },
      "highSlot": {
        "shotsOnGoal": 6,
        "goals": 0,
        "shootingPctg": 0.0,
        "sogPercentile": 0.4463,
        "goalsPercentile": 0.0
      },
      "leftCircle": {
        "shotsOnGoal": 2,
        "goals": 0,
        "shootingPctg": 0.0,
        "sogPercentile": 0.2199,
        "goalsPercentile": 0.0
      },
      "rightCircle": {
        "shotsOnGoal": 3,
        "goals": 0,
        "shootingPctg": 0.0,
        "sogPercentile": 0.3094,
        "goalsPercentile": 0.0
      },
      "cornerLeft": {
        "shotsOnGoal": 1,
        "goals": 0,
        "shootingPctg": 0.0,
        "sogPercentile": 0.1539,
        "goalsPercentile": 0.0
      },
      "cornerRight": {
        "shotsOnGoal": 0,
        "goals": 0,
        "shootingPctg": 0.0,
        "sogPercentile": 0.0,
        "goalsPercentile": 0.0
      },
      "pointLeft": {
        "shotsOnGoal": 0,
        "goals": 0,
        "shootingPctg": 0.0,
        "sogPercentile": 0.0,
        "goalsPercentile": 0.0
      },
      "pointRight": {
        "shotsOnGoal": 0,
        "goals": 0,
        "shootingPctg": 0.0,
        "sogPercentile": 0.0,
        "goalsPercentile": 0.0
      },
      "pointCenter": {
        "shotsOnGoal": 0,
        "goals": 0,
        "shootingPctg": 0.0,
        "sogPercentile": 0.0,
        "goalsPercentile": 0.0
      },
      "total": {
        "shotsOnGoal": 20,
        "goals": 2,
        "shootingPctg": 0.1
      },
      "totals": {
        "all": {
          "shotsOnGoal": 31,
          "goals": 2,
          "shootingPctg": 0.0645,
          "sogPercentile": 0.2834,
          "goalsPercentile": 0.2345,
          "sogLeagueAvg": 85.9138,
          "goalsLeagueAvg": 11.1545
        },
        "high": {
          "shotsOnGoal": 8,
          "goals": 2,
          "shootingPctg": 0.25,
          "sogPercentile": 0.2345,
          "goalsPercentile": 0.2834,
          "sogLeagueAvg": 31.6244,
          "goalsLeagueAvg": 6.1935
        },
        "long": {
          "shotsOnGoal": 0,
          "goals": 0,
          "shootingPctg": 0.0,
          "sogPercentile": 0.0,
          "goalsPercentile": 0.0,
          "sogLeagueAvg": 8.0081,
          "goalsLeagueAvg": 0.3106
        },
        "mid": {
          "shotsOnGoal": 11,
          "goals": 0,
          "shootingPctg": 0.0,
          "sogPercentile": 0.3469,
          "goalsPercentile": 0.0,
          "sogLeagueAvg": 27.2195,
          "goalsLeagueAvg": 3.3008
        }
      }
    },
    "l5": null,
    "l10": null,
    "l20": null
  },
  "playoffs": null
}