{
  "playerId": 8481032,
  "playerName": "Paul Cotter",
  "team": "AWAY",
  "season": 2025,
  "lastUpdated": "2026-06-13T03:03:42.315167",
  "reg": {
    "totalGames": 53,
    "szn": {
      "slot": {
        "shotsOnGoal": 12,
        "goals": 0,
        "attempts": 21,
        "xGoals": 1.31
      },
      "low": {
        "shotsOnGoal": 35,
        "goals": 9,
        "attempts": 60,
        "xGoals": 7.25
      },
      "lowLeft": {
        "shotsOnGoal": 3,
        "goals": 0,
        "attempts": 9,
        "xGoals": 0.14
      },
      "lowRight": {
        "shotsOnGoal": 6,
        "goals": 0,
        "attempts": 11,
        "xGoals": 0.21
      },
      "point": {
        "shotsOnGoal": 2,
        "goals": 0,
        "attempts": 2,
        "xGoals": 0.02
      },
      "left": {
        "shotsOnGoal": 2,
        "goals": 0,
        "attempts": 2,
        "xGoals": 0.02
      },
      "right": {
        "shotsOnGoal": 1,
        "goals": 0,
        "attempts": 1,
        "xGoals": 0.02
      },
      "total": {
        "shotsOnGoal": 61,
        "goals": 9,
        "attempts": 106,
        "xGoals": 8.96
      }
    },
    "l5": {
      "slot": {
        "shotsOnGoal": 1,
        "goals": 0,
        "attempts": 1,
        "xGoals": 0.07
      },
      "low": {
        "shotsOnGoal": 4,
        "goals": 1,
        "attempts": 8,
        "xGoals": 1.04
      },
      "lowLeft": {
        "shotsOnGoal": 0,
        "goals": 0,
        "attempts": 0,
        "xGoals": 0.0
      },
      "lowRight": {
        "shotsOnGoal": 1,
        "goals": 0,
        "attempts": 1,
        "xGoals": 0.01
      },
      "point": {
        "shotsOnGoal": 0,
        "goals": 0,
        "attempts": 0,
        "xGoals": 0.0
      },
      "left": {
        "shotsOnGoal": 0,
        "goals": 0,
        "attempts": 0,
        "xGoals": 0.0
      },
      "right": {
        "shotsOnGoal": 0,
        "goals": 0,
        "attempts": 0,
        "xGoals": 0.0
      },
      "total": {
        "shotsOnGoal": 6,
        "goals": 1,
        "attempts": 10,
        "xGoals": 1.12
      }
    },
    "l10": {
      "slot": {
        "shotsOnGoal": 1,
        "goals": 0,
        "attempts": 1,
        "xGoals": 0.07
      },
      "low": {
        "shotsOnGoal": 8,
        "goals": 3,
        "attempts": 15,
        "xGoals": 2.05
      },
      "lowLeft": {
        "shotsOnGoal": 0,
        "goals": 0,
        "attempts": 0,
        "xGoals": 0.0
      },
      "lowRight": {
        "shotsOnGoal": 1,
        "goals": 0,
        "attempts": 1,
        "xGoals": 0.01
      },
      "point": {
        "shotsOnGoal": 1,
        "goals": 0,
        "attempts": 1,
        "xGoals": 0.01
      },
      "left": {
        "shotsOnGoal": 0,
        "goals": 0,
        "attempts": 0,
        "xGoals": 0.0
      },
      "right": {
        "shotsOnGoal": 0,
        "goals": 0,
        "attempts": 0,
        "xGoals": 0.0
      },
      "total": {
        "shotsOnGoal": 11,
        "goals": 3,
        "attempts": 18,
        "xGoals": 2.14
      }
    },
    "l20": {
      "slot": {
        "shotsOnGoal": 4,
        "goals": 0,
        "attempts": 6,
        "xGoals": 0.36
      },
      "low": {
        "shotsOnGoal": 14,
        "goals": 4,
        "attempts": 25,
        "xGoals": 3.24
      },
      "lowLeft": {
        "shotsOnGoal": 0,
        "goals": 0,
        "attempts": 1,
        "xGoals": 0.02
      },
      "lowRight": {
        "shotsOnGoal": 2,
        "goals": 0,
        "attempts": 2,
        "xGoals": 0.04
      },
      "point": {
        "shotsOnGoal": 1,
        "goals": 0,
        "attempts": 1,
        "xGoals": 0.01
      },
      "left": {
        "shotsOnGoal": 0,
        "goals": 0,
        "attempts": 0,
        "xGoals": 0.0
      },
      "right": {
        "shotsOnGoal": 0,
        "goals": 0,
        "attempts": 0,
        "xGoals": 0.0
      },
      "total": {
        "shotsOnGoal": 21,
        "goals": 4,
        "attempts": 35,
        "xGoals": 3.66
      }
    }
  },
  "playoffs": null
}