{
  "playerId": 8475149,
  "playerName": "Marcus Johansson",
  "team": "MIN",
  "position": "L",
  "season": 2026,
  "lastUpdated": "2026-06-30T23:38:41.348385",
  "reg": {
    "totalGames": 75,
    "szn": {
      "slot": {
        "shotsOnGoal": 32,
        "goals": 8,
        "shootingPctg": 0.25,
        "sogPercentile": 0.5733,
        "goalsPercentile": 0.5912
      },
      "highSlot": {
        "shotsOnGoal": 10,
        "goals": 1,
        "shootingPctg": 0.1,
        "sogPercentile": 0.6189,
        "goalsPercentile": 0.4316
      },
      "leftCircle": {
        "shotsOnGoal": 12,
        "goals": 0,
        "shootingPctg": 0.0,
        "sogPercentile": 0.5464,
        "goalsPercentile": 0.0
      },
      "rightCircle": {
        "shotsOnGoal": 21,
        "goals": 4,
        "shootingPctg": 0.1905,
        "sogPercentile": 0.7402,
        "goalsPercentile": 0.8648
      },
      "cornerLeft": {
        "shotsOnGoal": 5,
        "goals": 0,
        "shootingPctg": 0.0,
        "sogPercentile": 0.4039,
        "goalsPercentile": 0.0
      },
      "cornerRight": {
        "shotsOnGoal": 5,
        "goals": 1,
        "shootingPctg": 0.2,
        "sogPercentile": 0.4137,
        "goalsPercentile": 0.4096
      },
      "pointLeft": {
        "shotsOnGoal": 4,
        "goals": 0,
        "shootingPctg": 0.0,
        "sogPercentile": 0.7215,
        "goalsPercentile": 0.0
      },
      "pointRight": {
        "shotsOnGoal": 2,
        "goals": 0,
        "shootingPctg": 0.0,
        "sogPercentile": 0.5033,
        "goalsPercentile": 0.0
      },
      "pointCenter": {
        "shotsOnGoal": 7,
        "goals": 0,
        "shootingPctg": 0.0,
        "sogPercentile": 0.6979,
        "goalsPercentile": 0.0
      },
      "total": {
        "shotsOnGoal": 98,
        "goals": 14,
        "shootingPctg": 0.1429
      },
      "totals": {
        "all": {
          "shotsOnGoal": 106,
          "goals": 15,
          "shootingPctg": 0.1415,
          "sogPercentile": 0.6433,
          "goalsPercentile": 0.6759,
          "sogLeagueAvg": 85.9138,
          "goalsLeagueAvg": 11.1545
        },
        "high": {
          "shotsOnGoal": 32,
          "goals": 8,
          "shootingPctg": 0.25,
          "sogPercentile": 0.5423,
          "goalsPercentile": 0.6384,
          "sogLeagueAvg": 31.6244,
          "goalsLeagueAvg": 6.1935
        },
        "long": {
          "shotsOnGoal": 9,
          "goals": 0,
          "shootingPctg": 0.0,
          "sogPercentile": 0.6564,
          "goalsPercentile": 0.0,
          "sogLeagueAvg": 8.0081,
          "goalsLeagueAvg": 0.3106
        },
        "mid": {
          "shotsOnGoal": 33,
          "goals": 4,
          "shootingPctg": 0.1212,
          "sogPercentile": 0.6596,
          "goalsPercentile": 0.6482,
          "sogLeagueAvg": 27.2195,
          "goalsLeagueAvg": 3.3008
        }
      }
    },
    "l5": null,
    "l10": null,
    "l20": null
  },
  "playoffs": {
    "totalGames": 11,
    "szn": {
      "slot": {
        "shotsOnGoal": 4,
        "goals": 1,
        "shootingPctg": 0.25,
        "sogPercentile": 0.2802,
        "goalsPercentile": 0.2937
      },
      "highSlot": {
        "shotsOnGoal": 3,
        "goals": 2,
        "shootingPctg": 0.6667,
        "sogPercentile": 0.7982,
        "goalsPercentile": 0.9552
      },
      "leftCircle": {
        "shotsOnGoal": 2,
        "goals": 1,
        "shootingPctg": 0.5,
        "sogPercentile": 0.3161,
        "goalsPercentile": 0.444
      },
      "rightCircle": {
        "shotsOnGoal": 2,
        "goals": 0,
        "shootingPctg": 0.0,
        "sogPercentile": 0.4664,
        "goalsPercentile": 0.0
      },
      "cornerLeft": {
        "shotsOnGoal": 0,
        "goals": 0,
        "shootingPctg": 0.0,
        "sogPercentile": 0.0,
        "goalsPercentile": 0.0
      },
      "cornerRight": {
        "shotsOnGoal": 0,
        "goals": 0,
        "shootingPctg": 0.0,
        "sogPercentile": 0.0,
        "goalsPercentile": 0.0
      },
      "pointLeft": {
        "shotsOnGoal": 1,
        "goals": 0,
        "shootingPctg": 0.0,
        "sogPercentile": 0.6502,
        "goalsPercentile": 0.0
      },
      "pointRight": {
        "shotsOnGoal": 0,
        "goals": 0,
        "shootingPctg": 0.0,
        "sogPercentile": 0.0,
        "goalsPercentile": 0.0
      },
      "pointCenter": {
        "shotsOnGoal": 6,
        "goals": 0,
        "shootingPctg": 0.0,
        "sogPercentile": 0.9641,
        "goalsPercentile": 0.0
      },
      "total": {
        "shotsOnGoal": 18,
        "goals": 4,
        "shootingPctg": 0.2222
      },
      "totals": {
        "all": {
          "shotsOnGoal": 18,
          "goals": 4,
          "shootingPctg": 0.2222,
          "sogPercentile": 0.6861,
          "goalsPercentile": 0.8296,
          "sogLeagueAvg": 15.1295,
          "goalsLeagueAvg": 1.8393
        },
        "high": {
          "shotsOnGoal": 4,
          "goals": 1,
          "shootingPctg": 0.25,
          "sogPercentile": 0.4798,
          "goalsPercentile": 0.5202,
          "sogLeagueAvg": 5.1518,
          "goalsLeagueAvg": 0.9554
        },
        "long": {
          "shotsOnGoal": 4,
          "goals": 0,
          "shootingPctg": 0.0,
          "sogPercentile": 0.8834,
          "goalsPercentile": 0.0,
          "sogLeagueAvg": 1.4554,
          "goalsLeagueAvg": 0.067
        },
        "mid": {
          "shotsOnGoal": 6,
          "goals": 3,
          "shootingPctg": 0.5,
          "sogPercentile": 0.6906,
          "goalsPercentile": 0.9507,
          "sogLeagueAvg": 4.6384,
          "goalsLeagueAvg": 0.5045
        }
      }
    },
    "l5": null,
    "l10": null,
    "l20": null
  }
}