{
  "playerId": 8480800,
  "playerName": "Quinn Hughes",
  "team": "VAN,MIN",
  "position": "D",
  "season": 2026,
  "lastUpdated": "2026-06-14T15:16:53.350926",
  "reg": {
    "totalGames": 74,
    "szn": {
      "slot": {
        "shotsOnGoal": 10,
        "goals": 2,
        "shootingPctg": 0.2,
        "sogPercentile": 0.4537,
        "goalsPercentile": 0.4213
      },
      "highSlot": {
        "shotsOnGoal": 28,
        "goals": 2,
        "shootingPctg": 0.0714,
        "sogPercentile": 0.9877,
        "goalsPercentile": 0.8519
      },
      "leftCircle": {
        "shotsOnGoal": 28,
        "goals": 0,
        "shootingPctg": 0.0,
        "sogPercentile": 0.9907,
        "goalsPercentile": 0.0
      },
      "rightCircle": {
        "shotsOnGoal": 9,
        "goals": 1,
        "shootingPctg": 0.1111,
        "sogPercentile": 0.8395,
        "goalsPercentile": 0.7562
      },
      "cornerLeft": {
        "shotsOnGoal": 5,
        "goals": 1,
        "shootingPctg": 0.2,
        "sogPercentile": 0.4923,
        "goalsPercentile": 0.4753
      },
      "cornerRight": {
        "shotsOnGoal": 3,
        "goals": 0,
        "shootingPctg": 0.0,
        "sogPercentile": 0.4738,
        "goalsPercentile": 0.0
      },
      "pointLeft": {
        "shotsOnGoal": 25,
        "goals": 0,
        "shootingPctg": 0.0,
        "sogPercentile": 0.8796,
        "goalsPercentile": 0.0
      },
      "pointRight": {
        "shotsOnGoal": 11,
        "goals": 0,
        "shootingPctg": 0.0,
        "sogPercentile": 0.6574,
        "goalsPercentile": 0.0
      },
      "pointCenter": {
        "shotsOnGoal": 41,
        "goals": 0,
        "shootingPctg": 0.0,
        "sogPercentile": 0.9599,
        "goalsPercentile": 0.0
      },
      "total": {
        "shotsOnGoal": 160,
        "goals": 6,
        "shootingPctg": 0.0375
      },
      "totals": {
        "all": {
          "shotsOnGoal": 187,
          "goals": 7,
          "shootingPctg": 0.0374,
          "sogPercentile": 0.9722,
          "goalsPercentile": 0.7901,
          "sogLeagueAvg": 62.1077,
          "goalsLeagueAvg": 3.7723
        },
        "high": {
          "shotsOnGoal": 10,
          "goals": 2,
          "shootingPctg": 0.2,
          "sogPercentile": 0.8735,
          "goalsPercentile": 0.8333,
          "sogLeagueAvg": 4.0369,
          "goalsLeagueAvg": 0.68
        },
        "long": {
          "shotsOnGoal": 77,
          "goals": 0,
          "shootingPctg": 0.0,
          "sogPercentile": 0.9259,
          "goalsPercentile": 0.0,
          "sogLeagueAvg": 31.6708,
          "goalsLeagueAvg": 1.1262
        },
        "mid": {
          "shotsOnGoal": 65,
          "goals": 3,
          "shootingPctg": 0.0462,
          "sogPercentile": 0.9877,
          "goalsPercentile": 0.784,
          "sogLeagueAvg": 13.4246,
          "goalsLeagueAvg": 1.4923
        }
      }
    },
    "l5": null,
    "l10": null,
    "l20": null
  },
  "playoffs": {
    "totalGames": 11,
    "szn": {
      "slot": {
        "shotsOnGoal": 2,
        "goals": 0,
        "shootingPctg": 0.0,
        "sogPercentile": 0.4426,
        "goalsPercentile": 0.0
      },
      "highSlot": {
        "shotsOnGoal": 3,
        "goals": 1,
        "shootingPctg": 0.3333,
        "sogPercentile": 0.9672,
        "goalsPercentile": 0.9098
      },
      "leftCircle": {
        "shotsOnGoal": 2,
        "goals": 1,
        "shootingPctg": 0.5,
        "sogPercentile": 0.8115,
        "goalsPercentile": 0.9344
      },
      "rightCircle": {
        "shotsOnGoal": 0,
        "goals": 0,
        "shootingPctg": 0.0,
        "sogPercentile": 0.0,
        "goalsPercentile": 0.0
      },
      "cornerLeft": {
        "shotsOnGoal": 1,
        "goals": 0,
        "shootingPctg": 0.0,
        "sogPercentile": 0.4385,
        "goalsPercentile": 0.0
      },
      "cornerRight": {
        "shotsOnGoal": 0,
        "goals": 0,
        "shootingPctg": 0.0,
        "sogPercentile": 0.0,
        "goalsPercentile": 0.0
      },
      "pointLeft": {
        "shotsOnGoal": 3,
        "goals": 0,
        "shootingPctg": 0.0,
        "sogPercentile": 0.7705,
        "goalsPercentile": 0.0
      },
      "pointRight": {
        "shotsOnGoal": 0,
        "goals": 0,
        "shootingPctg": 0.0,
        "sogPercentile": 0.0,
        "goalsPercentile": 0.0
      },
      "pointCenter": {
        "shotsOnGoal": 2,
        "goals": 1,
        "shootingPctg": 0.5,
        "sogPercentile": 0.6311,
        "goalsPercentile": 0.9426
      },
      "total": {
        "shotsOnGoal": 13,
        "goals": 3,
        "shootingPctg": 0.2308
      },
      "totals": {
        "all": {
          "shotsOnGoal": 20,
          "goals": 4,
          "shootingPctg": 0.2,
          "sogPercentile": 0.8279,
          "goalsPercentile": 0.959,
          "sogLeagueAvg": 9.9756,
          "goalsLeagueAvg": 0.6016
        },
        "high": {
          "shotsOnGoal": 2,
          "goals": 0,
          "shootingPctg": 0.0,
          "sogPercentile": 0.877,
          "goalsPercentile": 0.0,
          "sogLeagueAvg": 0.561,
          "goalsLeagueAvg": 0.0813
        },
        "long": {
          "shotsOnGoal": 5,
          "goals": 1,
          "shootingPctg": 0.2,
          "sogPercentile": 0.5902,
          "goalsPercentile": 0.8607,
          "sogLeagueAvg": 4.9106,
          "goalsLeagueAvg": 0.1789
        },
        "mid": {
          "shotsOnGoal": 5,
          "goals": 2,
          "shootingPctg": 0.4,
          "sogPercentile": 0.8525,
          "goalsPercentile": 0.959,
          "sogLeagueAvg": 2.0569,
          "goalsLeagueAvg": 0.2683
        }
      }
    },
    "l5": null,
    "l10": null,
    "l20": null
  }
}